{
  "Title": "Madame de Langeais",
  "Year": "1910",
  "Rated": "N/A",
  "Released": "N/A",
  "Runtime": "7 min",
  "Genre": "Short, Drama",
  "Director": "Andr\u00e9 Calmettes",
  "Writer": "N/A",
  "Actors": "Andr\u00e9 Calmettes, Germaine Dermoz",
  "Plot": "General de Montriveau is in love with the Duchess Antoinette de Langeais who refuses to accept him. Helped by the powerful group of Thirteen, he chases her to the monastery where she has taken refuge under the name of Sister Th\u00e9r\u00e8se.",
  "Language": "None",
  "Country": "France",
  "Awards": "N/A",
  "Poster": "N/A",
  "Ratings": [],
  "Metascore": "N/A",
  "imdbRating": "N/A",
  "imdbVotes": "N/A",
  "imdbID": "tt0000952",
  "Type": "movie",
  "DVD": "N/A",
  "BoxOffice": "N/A",
  "Production": "N/A",
  "Website": "N/A",
  "Response": "True"
}