{
  "Title": "Freezing Auntie",
  "Year": "1912",
  "Rated": "N/A",
  "Released": "05 Jan 1912",
  "Runtime": "6 min",
  "Genre": "Comedy, Sci-Fi, Short",
  "Director": "N/A",
  "Writer": "Marion Brooks",
  "Actors": "William West, Alice Washburn, Marion Brooks, Harold M. Shaw",
  "Plot": "An injection that can freeze cattle solid for later thawing is prepared by a woman's husband and nephew to be used on her. At her son-in-law's warning, she replaces the fluid with tap water and accepts the injection, faking the freezing, then tormenting them as a \"ghost.\"",
  "Language": "English",
  "Country": "USA",
  "Awards": "N/A",
  "Poster": "N/A",
  "Ratings": [],
  "Metascore": "N/A",
  "imdbRating": "N/A",
  "imdbVotes": "N/A",
  "imdbID": "tt0001629",
  "Type": "movie",
  "DVD": "N/A",
  "BoxOffice": "N/A",
  "Production": "N/A",
  "Website": "N/A",
  "Response": "True"
}