{
  "Title": "The Day After",
  "Year": "1909",
  "Rated": "N/A",
  "Released": "30 Dec 1909",
  "Runtime": "8 min",
  "Genre": "Short, Comedy",
  "Director": "D.W. Griffith",
  "Writer": "Mary Pickford",
  "Actors": "Arthur V. Johnson, Marion Leonard, W. Chrystie Miller",
  "Plot": "Mr. and Mrs. Hilton throw a New Year's Eve party. They agree not to drink the punch themselves, but as guests begin to arrive their resolve weakens, and soon they are both cavorting drunkenly. Next morning Mr. Hilton, feeling very sick, is conscience-stricken over his behavior. He fears to face his wife until he discovers that she feels just as guilty herself.",
  "Language": "None, English",
  "Country": "United States",
  "Awards": "N/A",
  "Poster": "https://m.media-amazon.com/images/M/MV5BNTI0YWJmNjEtODdkNy00ZjVhLWJkNDgtOGIxZjI4ODEzMmUxXkEyXkFqcGdeQXVyMTAyNjc3NDgy._V1_SX300.jpg",
  "Ratings": [
    {
      "Source": "Internet Movie Database",
      "Value": "5.2/10"
    }
  ],
  "Metascore": "N/A",
  "imdbRating": "5.2",
  "imdbVotes": "81",
  "imdbID": "tt0000841",
  "Type": "movie",
  "DVD": "N/A",
  "BoxOffice": "N/A",
  "Production": "N/A",
  "Website": "N/A",
  "Response": "True"
}