{
  "Title": "The Helping Hand",
  "Year": "1908",
  "Rated": "N/A",
  "Released": "29 Dec 1908",
  "Runtime": "15 min",
  "Genre": "Short, Drama",
  "Director": "D.W. Griffith",
  "Writer": "D.W. Griffith",
  "Actors": "Flora Finch, Linda Arvidson, Anita Hendrie",
  "Plot": "This is the year that the motion picture industry officially started, spearheaded by the 33 year old Griffith. He had totaled up over 80 films in this one year, and this film was the last for 1908. In it, you notice how he brings out the 'inner light' from his performers, probing their emotions in the roles that they play.",
  "Language": "None, English",
  "Country": "United States",
  "Awards": "N/A",
  "Poster": "N/A",
  "Ratings": [
    {
      "Source": "Internet Movie Database",
      "Value": "6.0/10"
    }
  ],
  "Metascore": "N/A",
  "imdbRating": "6.0",
  "imdbVotes": "27",
  "imdbID": "tt0000699",
  "Type": "movie",
  "DVD": "N/A",
  "BoxOffice": "N/A",
  "Production": "N/A",
  "Website": "N/A",
  "Response": "True"
}