{
  "Title": "We Must Do Our Best",
  "Year": "1909",
  "Rated": "N/A",
  "Released": "N/A",
  "Runtime": "10 min",
  "Genre": "Short, Comedy",
  "Director": "Van Dyke Brooke",
  "Writer": "N/A",
  "Actors": "Kenneth Casey, Moe Howard",
  "Plot": "N/A",
  "Language": "None",
  "Country": "United States",
  "Awards": "N/A",
  "Poster": "N/A",
  "Ratings": [
    {
      "Source": "Internet Movie Database",
      "Value": "8.0/10"
    }
  ],
  "Metascore": "N/A",
  "imdbRating": "8.0",
  "imdbVotes": "38",
  "imdbID": "tt0001089",
  "Type": "movie",
  "DVD": "N/A",
  "BoxOffice": "N/A",
  "Production": "N/A",
  "Website": "N/A",
  "Response": "True"
}