{
  "Title": "The Apache Renegade",
  "Year": "1912",
  "Rated": "N/A",
  "Released": "28 Sep 1912",
  "Runtime": "N/A",
  "Genre": "Short, Western, Adventure",
  "Director": "George Melford",
  "Writer": "N/A",
  "Actors": "Carlyle Blackwell, Kate Winston, William H. West, Knute Rahm",
  "Plot": "Mary Simmons, journeying through the Apache country with her brother's wagon train, meets Jack Lane, a cowboy, who expresses his desire to accompany the party through the Indian lands. ...",
  "Language": "None, English",
  "Country": "USA",
  "Awards": "N/A",
  "Poster": "https://m.media-amazon.com/images/M/MV5BNDJjNmQ2MDUtMjAxOS00YzIzLWEzYzMtMDNkNjRkMTQ1MjNkL2ltYWdlXkEyXkFqcGdeQXVyMDUyOTUyNQ@@._V1_SX300.jpg",
  "Ratings": [],
  "Metascore": "N/A",
  "imdbRating": "N/A",
  "imdbVotes": "N/A",
  "imdbID": "tt0002027",
  "Type": "movie",
  "DVD": "N/A",
  "BoxOffice": "N/A",
  "Production": "N/A",
  "Website": "N/A",
  "Response": "True"
}