{
  "Title": "How Jim Proposed",
  "Year": "1912",
  "Rated": "N/A",
  "Released": "24 Jan 1912",
  "Runtime": "N/A",
  "Genre": "Short, Comedy, Romance",
  "Director": "Pat Hartigan",
  "Writer": "N/A",
  "Actors": "Ruth Roland, Marshall Neilan",
  "Plot": "Jim was all right and could have had the girl for the asking, but whenever he got ready to propose some unfortunate accident occurred that would frustrate his plans and make him ridiculous before the girl of his choice.",
  "Language": "None, English",
  "Country": "United States",
  "Awards": "N/A",
  "Poster": "N/A",
  "Ratings": [],
  "Metascore": "N/A",
  "imdbRating": "N/A",
  "imdbVotes": "N/A",
  "imdbID": "tt0002258",
  "Type": "movie",
  "DVD": "N/A",
  "BoxOffice": "N/A",
  "Production": "N/A",
  "Website": "N/A",
  "Response": "True"
}