{
  "Title": "The Last Drop of Water",
  "Year": "1911",
  "Rated": "Not Rated",
  "Released": "27 Jul 1911",
  "Runtime": "18 min",
  "Genre": "Short, Western",
  "Director": "D.W. Griffith",
  "Writer": "Bret Harte, Stanner E.V. Taylor",
  "Actors": "Blanche Sweet, Charles West, Joseph Graybill",
  "Plot": "A wagon train heading west across the great desert runs out of water, and is attacked by Indians. One man -- their last hope -- is sent out to find water.",
  "Language": "None, English",
  "Country": "United States",
  "Awards": "N/A",
  "Poster": "https://m.media-amazon.com/images/M/MV5BMDlmYzgwZmItNzdlMS00ZmE5LThkYmUtYmNhNjAyY2FlMmFiXkEyXkFqcGdeQXVyMTYxNjkxOQ@@._V1_SX300.jpg",
  "Ratings": [
    {
      "Source": "Internet Movie Database",
      "Value": "5.8/10"
    }
  ],
  "Metascore": "N/A",
  "imdbRating": "5.8",
  "imdbVotes": "280",
  "imdbID": "tt0001724",
  "Type": "movie",
  "DVD": "N/A",
  "BoxOffice": "N/A",
  "Production": "N/A",
  "Website": "N/A",
  "Response": "True"
}